easyscrape/__init__.py
easyscrape/async_core.py
easyscrape/breaker.py
easyscrape/browser.py
easyscrape/cache.py
easyscrape/cli.py
easyscrape/config.py
easyscrape/constants.py
easyscrape/core.py
easyscrape/dashboard.py
easyscrape/exceptions.py
easyscrape/export.py
easyscrape/extractors.py
easyscrape/hooks.py
easyscrape/log.py
easyscrape/pagination.py
easyscrape/pool.py
easyscrape/py.typed
easyscrape/rate_limiter.py
easyscrape/retry.py
easyscrape/robots.py
easyscrape/session.py
easyscrape/stats.py
easyscrape/user_agents.py
easyscrape/utils.py
easyscrape/validate.py
easyscrape_py-0.1.1.dist-info/METADATA
easyscrape_py-0.1.1.dist-info/WHEEL
easyscrape_py-0.1.1.dist-info/entry_points.txt
easyscrape_py-0.1.1.dist-info/licenses/LICENSE
easyscrape_py-0.1.1.dist-info/RECORD
