Metadata-Version: 2.4
Name: easyscrape-py
Version: 0.1.1
Summary: Fast, secure web scraping for Python
Project-URL: Homepage, https://github.com/doudol/easyscrape
Project-URL: Documentation, https://easyscrape.readthedocs.io
Project-URL: Repository, https://github.com/doudol/easyscrape
Project-URL: Changelog, https://github.com/doudol/easyscrape/blob/main/CHANGELOG.md
Author: EasyScrape Contributors
License-Expression: MIT
License-File: LICENSE
Keywords: async,crawler,http,scraping,web-scraping
Classifier: Development Status :: 4 - Beta
Classifier: Intended Audience :: Developers
Classifier: License :: OSI Approved :: MIT License
Classifier: Operating System :: OS Independent
Classifier: Programming Language :: Python :: 3
Classifier: Programming Language :: Python :: 3.9
Classifier: Programming Language :: Python :: 3.10
Classifier: Programming Language :: Python :: 3.11
Classifier: Programming Language :: Python :: 3.12
Classifier: Topic :: Internet :: WWW/HTTP
Classifier: Topic :: Software Development :: Libraries :: Python Modules
Classifier: Typing :: Typed
Requires-Python: >=3.9
Requires-Dist: httpx>=0.25.0
Requires-Dist: httpx[http2]>=0.25.0
Requires-Dist: lxml>=4.9.0
Requires-Dist: selectolax>=0.3.17
Provides-Extra: all
Requires-Dist: easyscrape[browser,dev,export,stealth]; extra == 'all'
Provides-Extra: browser
Requires-Dist: playwright>=1.40.0; extra == 'browser'
Provides-Extra: dev
Requires-Dist: build>=1.0.0; extra == 'dev'
Requires-Dist: mypy>=1.7.0; extra == 'dev'
Requires-Dist: pre-commit>=3.5.0; extra == 'dev'
Requires-Dist: pytest-asyncio>=0.21.0; extra == 'dev'
Requires-Dist: pytest-cov>=4.1.0; extra == 'dev'
Requires-Dist: pytest>=7.4.0; extra == 'dev'
Requires-Dist: respx>=0.20.0; extra == 'dev'
Requires-Dist: ruff>=0.1.0; extra == 'dev'
Requires-Dist: twine>=4.0.0; extra == 'dev'
Provides-Extra: export
Requires-Dist: openpyxl>=3.1.0; extra == 'export'
Requires-Dist: pandas>=2.0.0; extra == 'export'
Requires-Dist: pyarrow>=14.0.0; extra == 'export'
Provides-Extra: stealth
Requires-Dist: curl-cffi>=0.5.0; extra == 'stealth'
